{
  "cloudfirebase": {
    "title": "CloudFirebase",
    "type": "page",
    "theme": {
      "pagination": false
    }
  },
  "capturelogger": {
    "title": "CaptureLogger",
    "type": "page",
    "theme": {
      "pagination": false
    }
  },
  "youdramalist": {
    "title": "YouDramaList",
    "type": "page",
    "theme": {
      "pagination": false
    }
  },
  "receiverfeedback": {
    "title": "ReceiverFeedback",
    "type": "page",
    "theme": {
      "pagination": false
    }
  },
  "sendernotification": {
    "title": "SenderNotification",
    "type": "page",
    "theme": {
      "pagination": false
    }
  },
  "package": "Package"
}